swaglyrics/USING.txt
swaglyrics/__init__.py
swaglyrics/__main__.py
swaglyrics/cli.py
swaglyrics/tab.py
swaglyrics/static/favicon.ico
swaglyrics/static/songChanged.js
swaglyrics/static/style.css
swaglyrics/templates/lyrics.html
swaglyrics-1.2.2.dist-info/LICENSE.md
swaglyrics-1.2.2.dist-info/METADATA
swaglyrics-1.2.2.dist-info/WHEEL
swaglyrics-1.2.2.dist-info/entry_points.txt
swaglyrics-1.2.2.dist-info/top_level.txt
swaglyrics-1.2.2.dist-info/RECORD
