Metadata-Version: 2.1
Name: swaglyrics
Version: 1.2.2
Summary: Fetch the currently playing song from Spotify and display the lyrics in terminal or a browser tab. Very fast.
Home-page: https://github.com/SwagLyrics/SwagLyrics-For-Spotify
Author: Aadi Bajpai
Author-email: aadi@swaglyrics.dev
License: MIT
Project-URL: Documentation, https://swaglyrics.dev
Project-URL: Funding, https://www.paypal.me/sendclash
Project-URL: Source, https://github.com/SwagLyrics/SwagLyrics-For-Spotify
Project-URL: Tracker, https://github.com/SwagLyrics/SwagLyrics-For-Spotify/issues
Keywords: spotify lyrics python genius
Platform: UNKNOWN
Classifier: Programming Language :: Python :: 3
Classifier: Programming Language :: Python :: 3.6
Classifier: Programming Language :: Python :: 3.7
Classifier: Programming Language :: Python :: 3.8
Classifier: Framework :: Flask
Classifier: License :: OSI Approved :: MIT License
Classifier: Operating System :: OS Independent
Classifier: Intended Audience :: End Users/Desktop
Requires-Python: >=3.6
Requires-Dist: SwSpotify (>=1.2.0)
Requires-Dist: flask (==1.1.2)
Requires-Dist: requests (>=2.24.0)
Requires-Dist: unidecode (==1.1.1)
Requires-Dist: beautifulsoup4 (==4.9.1)
Requires-Dist: colorama (==0.4.3)
Provides-Extra: dev
Requires-Dist: mock ; extra == 'dev'
Requires-Dist: pytest ; extra == 'dev'
Requires-Dist: pytest-cov ; extra == 'dev'
Requires-Dist: blinker ; extra == 'dev'
Requires-Dist: Werkzeug (==1.0.1) ; extra == 'dev'
Requires-Dist: flask-testing ; extra == 'dev'
Requires-Dist: mypy ; extra == 'dev'
